{"name":"Levelapp sample02","tagline":"enchant.jsの書き方サンプル","body":"<!doctype html>\r\n<html>\r\n<head>\r\n    <meta charset=\"UTF-8\">\r\n    <link rel='stylesheet' href='style.css' type='text/css'>\r\n    <script src='js/enchant.js'></script>\r\n    <script src='js/plugins/nineleap.enchant.js'></script>\r\n    <script src='js/plugins/tl.enchant.js'></script>\r\n    <script src='js/plugins/ui.enchant.js'></script>\r\n    <script src='js/main.js'></script>\r\n    <title>untitled</title>\r\n</head>\r\n<body>\r\n</body>\r\n</html>\r\n","google":"","note":"Don't delete this file! It's used internally to help with page regeneration."}